py_document_chunker/__init__.py
py_document_chunker/base.py
py_document_chunker/core.py
py_document_chunker/tokenizers.py
py_document_chunker/utils.py
py_document_chunker/integrations/__init__.py
py_document_chunker/integrations/langchain.py
py_document_chunker/integrations/llamaindex.py
py_document_chunker/strategies/__init__.py
py_document_chunker/strategies/code.py
py_document_chunker/strategies/fixed_size.py
py_document_chunker/strategies/recursive.py
py_document_chunker/strategies/semantic.py
py_document_chunker/strategies/sentence.py
py_document_chunker/strategies/spacy_sentence.py
py_document_chunker/strategies/structure/__init__.py
py_document_chunker/strategies/structure/html.py
py_document_chunker/strategies/structure/markdown.py
py_document_chunker-0.3.0.dist-info/licenses/LICENSE
py_document_chunker-0.3.0.dist-info/licenses/NOTICE
py_document_chunker-0.3.0.dist-info/METADATA
py_document_chunker-0.3.0.dist-info/WHEEL
py_document_chunker-0.3.0.dist-info/top_level.txt
py_document_chunker-0.3.0.dist-info/RECORD
