Metadata-Version: 2.4
Name: py_document_chunker
Version: 0.3.0
Summary: A state-of-the-art Python package for advanced text segmentation (chunking).
Author-email: Gowtham Rao <rao@ohdsi.org>
License:                                  Apache License
Project-URL: Homepage, https://github.com/OHDSI/py_document_chunker
Project-URL: Bug Tracker, https://github.com/OHDSI/py_document_chunker/issues
Keywords: text chunking,text splitting,RAG,Retrieval-Augmented Generation,NLP,natural language processing,document processing,langchain,llamaindex
Classifier: Programming Language :: Python :: 3
Classifier: Operating System :: OS Independent
Classifier: Topic :: Text Processing
Classifier: Topic :: Scientific/Engineering :: Artificial Intelligence
Requires-Python: >=3.8
License-File: LICENSE
License-File: NOTICE
Requires-Dist: beautifulsoup4>=4.12.3
Requires-Dist: lxml>=5.2.0
Provides-Extra: nlp
Requires-Dist: nltk>3.8.1; extra == "nlp"
Provides-Extra: spacy
Requires-Dist: spacy==3.7.2; extra == "spacy"
Provides-Extra: semantic
Requires-Dist: numpy<2.0.0; extra == "semantic"
Provides-Extra: code
Requires-Dist: tree-sitter>=0.21.0; extra == "code"
Requires-Dist: tree-sitter-language-pack>=0.3.0; extra == "code"
Provides-Extra: markdown
Requires-Dist: markdown-it-py>=3.0.0; extra == "markdown"
Provides-Extra: html
Requires-Dist: html5lib>=1.1; extra == "html"
Provides-Extra: langchain
Requires-Dist: langchain-core; extra == "langchain"
Provides-Extra: llamaindex
Requires-Dist: llama-index-core>=0.12.29; extra == "llamaindex"
Provides-Extra: tokenizers
Requires-Dist: tiktoken>=0.7.0; extra == "tokenizers"
Provides-Extra: dev
Requires-Dist: pytest>=8.0.0; extra == "dev"
Requires-Dist: pytest-cov>=5.0.0; extra == "dev"
Requires-Dist: py_document_chunker[code,html,langchain,llamaindex,markdown,nlp,semantic,spacy,tokenizers]; extra == "dev"
Requires-Dist: black>=24.0.0; extra == "dev"
Requires-Dist: ruff>=0.1.0; extra == "dev"
Requires-Dist: pre-commit>=3.0.0; extra == "dev"
Dynamic: license-file
